yala_events_mcp/__init__.py
yala_events_mcp/api.py
yala_events_mcp/server.py
yala_events_mcp-0.2.1.dist-info/METADATA
yala_events_mcp-0.2.1.dist-info/WHEEL
yala_events_mcp-0.2.1.dist-info/entry_points.txt
yala_events_mcp-0.2.1.dist-info/licenses/LICENSE
yala_events_mcp-0.2.1.dist-info/RECORD
