Metadata-Version: 2.4
Name: yala-events-mcp
Version: 0.2.1
Summary: YALA Events MCP Server with stdio transport
Author: YALA Team
License-Expression: MIT
License-File: LICENSE
Requires-Python: >=3.11
Requires-Dist: httpx>=0.28.1
Requires-Dist: mcp[cli]>=1.6.0
Requires-Dist: python-dotenv>=1.0.0
